adore/__init__.py
adore/abt_storytelling.py
adore/contribution_calculating.py
adore/core.py
adore/image_data_processing.py
adore/preprocessing.py
adore/sparse_matrix_processing.py
adore/storytelling.py
adore/tabular_data_processing.py
adore/text_data_processing.py
adore/utils.py
adore/visualizing.py
adore-0.0.1.dist-info/licenses/LICENSE
adore-0.0.1.dist-info/METADATA
adore-0.0.1.dist-info/WHEEL
adore-0.0.1.dist-info/top_level.txt
adore-0.0.1.dist-info/RECORD
