Metadata-Version: 2.4
Name: adore
Version: 0.0.1
Summary: Adaptive Derivative Order Randomized Explanation
Author: Lemen Chao, Anran Fang, Ming Lei
Author-email: chaolemen@ruc.edu.cn
License: GPL-3.0
Requires-Python: >=3.10
License-File: LICENSE
Requires-Dist: numpy~=1.26.4
Requires-Dist: scipy~=1.14.1
Requires-Dist: joblib~=1.4.2
Requires-Dist: scikit-learn~=1.5.2
Requires-Dist: matplotlib~=3.10.0
Requires-Dist: seaborn~=0.13.2
Requires-Dist: pandas~=2.2.3
Requires-Dist: opencv-python~=4.10.0.84
Requires-Dist: spacy~=3.8.0
Requires-Dist: nltk~=3.9.1
Requires-Dist: keybert~=0.8.5
Requires-Dist: tensorflow~=2.18.0
Requires-Dist: tf-keras~=2.18.0
Requires-Dist: torch~=2.5.1
Requires-Dist: transformers~=4.46.3
Requires-Dist: pyspellchecker~=0.7.2
Requires-Dist: tensorflow-datasets~=4.9
Provides-Extra: dev
Requires-Dist: pytest; extra == "dev"
Requires-Dist: flake8; extra == "dev"
Dynamic: author
Dynamic: author-email
Dynamic: description
Dynamic: description-content-type
Dynamic: license
Dynamic: license-file
Dynamic: provides-extra
Dynamic: requires-dist
Dynamic: requires-python
Dynamic: summary
